feedsbot/__init__.py
feedsbot/__main__.py
feedsbot/_version.py
feedsbot/hooks.py
feedsbot/orm.py
feedsbot/util.py
feedsbot-0.7.0.dist-info/LICENSE
feedsbot-0.7.0.dist-info/METADATA
feedsbot-0.7.0.dist-info/WHEEL
feedsbot-0.7.0.dist-info/entry_points.txt
feedsbot-0.7.0.dist-info/top_level.txt
feedsbot-0.7.0.dist-info/RECORD
