Metadata-Version: 2.1
Name: feedsbot
Version: 0.7.0
Summary: Subscribe to RSS/Atom feeds in Delta Chat
Author-email: adbenitez <adb@merlinux.eu>
Project-URL: Homepage, https://github.com/deltachat-bot/feedsbot
Keywords: deltachat,bot,feeds,rss,atom
Classifier: Development Status :: 4 - Beta
Classifier: Programming Language :: Python :: 3
Classifier: License :: OSI Approved :: Mozilla Public License 2.0 (MPL 2.0)
Requires-Python: >=3.8
License-File: LICENSE
Requires-Dist: deltabot-cli <7.0,>=6.1.0
Requires-Dist: SQLAlchemy <3.0,>=2.0.25
Requires-Dist: feedparser <7.0,>=6.0.11
Requires-Dist: requests <3.0,>=2.28.1
Requires-Dist: beautifulsoup4 <5.0,>=4.11.1
Requires-Dist: html5lib >=1.1
Provides-Extra: dev
Requires-Dist: black ; extra == 'dev'
Requires-Dist: mypy ; extra == 'dev'
Requires-Dist: isort ; extra == 'dev'
Requires-Dist: pylint ; extra == 'dev'
Requires-Dist: pylama ; extra == 'dev'
Requires-Dist: pytest ; extra == 'dev'
Requires-Dist: types-requests ; extra == 'dev'
